baseten_inference_client-0.0.1.dist-info/METADATA
baseten_inference_client-0.0.1.dist-info/WHEEL
baseten_inference_client/__init__.py
baseten_inference_client/__init__.pyi
baseten_inference_client/baseten_inference_client.abi3.so
baseten_inference_client/py.typed
baseten_inference_client-0.0.1.dist-info/RECORD
